radbsdf.cp37-win_amd64.pyd
radbsdf-0.0.3.dist-info/License.txt
radbsdf-0.0.3.dist-info/METADATA
radbsdf-0.0.3.dist-info/WHEEL
radbsdf-0.0.3.dist-info/top_level.txt
radbsdf-0.0.3.dist-info/RECORD
